pytest_retry/__init__.py
pytest_retry/configs.py
pytest_retry/hooks.py
pytest_retry/py.typed
pytest_retry/retry_plugin.py
pytest_retry/server.py
pytest_retry-1.6.3.dist-info/LICENSE
pytest_retry-1.6.3.dist-info/METADATA
pytest_retry-1.6.3.dist-info/WHEEL
pytest_retry-1.6.3.dist-info/entry_points.txt
pytest_retry-1.6.3.dist-info/top_level.txt
pytest_retry-1.6.3.dist-info/RECORD
