Metadata-Version: 2.1
Name: pytest-retry
Version: 1.6.3
Summary: Adds the ability to retry flaky tests in CI environments
Author: str0zzapreti
License: MIT License
Project-URL: Homepage, https://github.com/str0zzapreti/pytest-retry
Keywords: rerun,pytest,flaky
Classifier: License :: OSI Approved :: MIT License
Classifier: Intended Audience :: Developers
Classifier: Programming Language :: Python
Classifier: Programming Language :: Python :: 3.9
Classifier: Programming Language :: Python :: 3.10
Classifier: Programming Language :: Python :: 3.11
Classifier: Programming Language :: Python :: 3 :: Only
Classifier: Framework :: Pytest
Requires-Python: >=3.9
License-File: LICENSE
Requires-Dist: pytest>=7.0.0
Provides-Extra: dev
Requires-Dist: black; extra == "dev"
Requires-Dist: isort; extra == "dev"
Requires-Dist: mypy; extra == "dev"
Requires-Dist: flake8; extra == "dev"
